athena/__init__.py
athena/dataset/__init__.py
athena/dataset/_utils.py
athena/dataset/datasets.py
athena/graph_builder/__init__.py
athena/graph_builder/base_graph_builder.py
athena/graph_builder/constants.py
athena/graph_builder/contact_graph_builder.py
athena/graph_builder/graphBuilder.py
athena/graph_builder/knn_graph_builder.py
athena/graph_builder/mappings.py
athena/graph_builder/radius_graph_builder.py
athena/metrics/__init__.py
athena/metrics/constants.py
athena/metrics/utils.py
athena/metrics/graph/__init__.py
athena/metrics/graph/graph.py
athena/metrics/heterogeneity/__init__.py
athena/metrics/heterogeneity/base_metrics.py
athena/metrics/heterogeneity/metrics.py
athena/neighborhood/__init__.py
athena/neighborhood/base_estimators.py
athena/neighborhood/estimators.py
athena/neighborhood/utils.py
athena/plotting/__init__.py
athena/plotting/utils.py
athena/plotting/visualization.py
athena/preprocessing/__init__.py
athena/preprocessing/_preprocessors.py
athena/preprocessing/preprocess.py
athena/utils/__init__.py
athena/utils/general.py
athena/utils/docs/__init__.py
athena/utils/docs/default_docs.py
athena/utils/tools/__init__.py
athena/utils/tools/graph.py
athena/utils/tools/image.py
athena/utils/tools/metric.py
ai4scr_athena-0.1.3.dist-info/METADATA
ai4scr_athena-0.1.3.dist-info/WHEEL
ai4scr_athena-0.1.3.dist-info/top_level.txt
ai4scr_athena-0.1.3.dist-info/RECORD
