Metadata-Version: 2.1
Name: ai4scr-athena
Version: 0.1.3
Summary: ATHENA package provides methods to analyse spatial heterogeneity in spatial omics data
Home-page: https://github.com/AI4SCR/ATHENA
Author: Adriano Martinelli
Author-email: art@zurich.ibm.com
Requires-Dist: scanpy (>=1.9.1)
Requires-Dist: scikit-image (>=0.19.2)
Requires-Dist: scikit-learn (>=1.0.2)
Requires-Dist: scipy (>=1.8.0)
Requires-Dist: numpy (>=1.21.6)
Requires-Dist: pandas (>=1.2)
Requires-Dist: networkx (>=2.8)
Requires-Dist: h5py (>=3.6.0)
Requires-Dist: tables (>=3.7.0)
Requires-Dist: astropy (>=5.0.4)
Requires-Dist: tqdm (>=4.64.0)
Requires-Dist: napari[all] (>=0.4.15)
Requires-Dist: seaborn (>=0.11.2)
Requires-Dist: squidpy (>=1.2.0)
Provides-Extra: dev
Requires-Dist: pytest (==6.2.4) ; extra == 'dev'
Requires-Dist: pytest-cov (==2.11.1) ; extra == 'dev'
Requires-Dist: black (==21.5b0) ; extra == 'dev'
Requires-Dist: flake8 (==3.9.1) ; extra == 'dev'
Requires-Dist: mypy (==0.812) ; extra == 'dev'
Requires-Dist: sphinx (==3.5.4) ; extra == 'dev'
Requires-Dist: sphinx-autodoc-typehints (==1.12.0) ; extra == 'dev'
Requires-Dist: better-apidoc (==0.3.1) ; extra == 'dev'
Requires-Dist: six (==1.16.0) ; extra == 'dev'
Requires-Dist: sphinx-rtd-theme (==0.5.2) ; extra == 'dev'
Requires-Dist: myst-parser (==0.14) ; extra == 'dev'
Requires-Dist: nbconvert (==6.5.0) ; extra == 'dev'
Requires-Dist: Jinja2 (<3.1) ; extra == 'dev'
Requires-Dist: jupyterlab (==3.3.4) ; extra == 'dev'
Requires-Dist: colorcet (==3.0.0) ; extra == 'dev'
Requires-Dist: twine ; extra == 'dev'
Provides-Extra: test
Requires-Dist: pytest ; extra == 'test'
Requires-Dist: pytest-cov ; extra == 'test'
Provides-Extra: vcs
